nonebot/adapters/bilibili_live/__init__.py
nonebot/adapters/bilibili_live/adapter.py
nonebot/adapters/bilibili_live/bot.py
nonebot/adapters/bilibili_live/config.py
nonebot/adapters/bilibili_live/const.py
nonebot/adapters/bilibili_live/event.py
nonebot/adapters/bilibili_live/exception.py
nonebot/adapters/bilibili_live/log.py
nonebot/adapters/bilibili_live/message.py
nonebot/adapters/bilibili_live/packet.py
nonebot/adapters/bilibili_live/utils.py
nonebot/adapters/bilibili_live/wbi.py
nonebot/adapters/bilibili_live/models/__init__.py
nonebot/adapters/bilibili_live/models/event.py
nonebot/adapters/bilibili_live/models/open.py
nonebot/adapters/bilibili_live/models/room.py
nonebot/adapters/bilibili_live/models/user_manage.py
nonebot/adapters/bilibili_live/pb/__init__.py
nonebot/adapters/bilibili_live/pb/fans_club.py
nonebot/adapters/bilibili_live/pb/interact_word_v2.py
nonebot/adapters/bilibili_live/pb/online_rank_v3.py
nonebot/adapters/bilibili_live/pb/user_dagw.py
nonebot_adapter_bilibili_live-0.2.4.dist-info/licenses/LICENSE
nonebot_adapter_bilibili_live-0.2.4.dist-info/METADATA
nonebot_adapter_bilibili_live-0.2.4.dist-info/WHEEL
nonebot_adapter_bilibili_live-0.2.4.dist-info/top_level.txt
nonebot_adapter_bilibili_live-0.2.4.dist-info/RECORD
