Metadata-Version: 2.4
Name: nonebot-adapter-bilibili-live
Version: 0.2.4
Summary: bilibili 直播间协议支持
Author-email: MingxuanGame <MingxuanGame@outlook.com>
License-Expression: MIT
Project-URL: Homepage, https://github.com/MingxuanGame/nonebot-adapter-bilibili-live
Project-URL: Repository, https://github.com/MingxuanGame/nonebot-adapter-bilibili-live
Project-URL: Documentation, https://github.com/MingxuanGame/nonebot-adapter-bilibili-live
Project-URL: Issues, https://github.com/MingxuanGame/nonebot-adapter-bilibili-live/issues
Project-URL: Changelog, https://github.com/MingxuanGame/nonebot-adapter-bilibili-live/releases
Keywords: nonebot,bilibili,live,adapter
Classifier: Development Status :: 3 - Alpha
Classifier: Framework :: Robot Framework
Classifier: Framework :: Robot Framework :: Library
Classifier: Operating System :: OS Independent
Classifier: Programming Language :: Python :: 3
Classifier: Topic :: Communications :: Chat
Requires-Python: >=3.9
License-File: LICENSE
Requires-Dist: betterproto>=1.2.5
Requires-Dist: brotli>=1.1.0
Requires-Dist: nonebot2>=2.4.2
Dynamic: license-file
